geneweaver/db/__init__.py
geneweaver/db/aio/__init__.py
geneweaver/db/aio/gene.py
geneweaver/db/aio/geneset.py
geneweaver/db/aio/ontology.py
geneweaver/db/aio/project.py
geneweaver/db/aio/publication.py
geneweaver/db/aio/search.py
geneweaver/db/aio/species.py
geneweaver/db/aio/threshold.py
geneweaver/db/core/__init__.py
geneweaver/db/core/cursor.py
geneweaver/db/core/settings.py
geneweaver/db/core/settings_class.py
geneweaver/db/exceptions.py
geneweaver/db/gene.py
geneweaver/db/geneset.py
geneweaver/db/geneset_value.py
geneweaver/db/monitor/__init__.py
geneweaver/db/monitor/db_health.py
geneweaver/db/ontology.py
geneweaver/db/project.py
geneweaver/db/publication.py
geneweaver/db/query/__init__.py
geneweaver/db/query/const.py
geneweaver/db/query/gene.py
geneweaver/db/query/geneset/__init__.py
geneweaver/db/query/geneset/const.py
geneweaver/db/query/geneset/read.py
geneweaver/db/query/geneset/utils.py
geneweaver/db/query/geneset/write.py
geneweaver/db/query/ontology.py
geneweaver/db/query/project.py
geneweaver/db/query/publication.py
geneweaver/db/query/search/__init__.py
geneweaver/db/query/search/const.py
geneweaver/db/query/search/search.py
geneweaver/db/query/search/utils.py
geneweaver/db/query/species.py
geneweaver/db/query/threshold.py
geneweaver/db/query/utils.py
geneweaver/db/search.py
geneweaver/db/species.py
geneweaver/db/threshold.py
geneweaver/db/user.py
geneweaver/db/utils.py
geneweaver_db-0.5.0.dist-info/LICENSE
geneweaver_db-0.5.0.dist-info/METADATA
geneweaver_db-0.5.0.dist-info/WHEEL
geneweaver_db-0.5.0.dist-info/RECORD
