Metadata-Version: 2.1
Name: geneweaver-db
Version: 0.5.0
Summary: Database Interaction Services for GeneWeaver
Home-page: https://thejacksonlaboratory.github.io/geneweaver-docs/
License: Apache-2.0
Author: Jax Computational Sciences
Author-email: cssc@jax.org
Requires-Python: >=3.9,<4.0
Classifier: License :: OSI Approved :: Apache Software License
Classifier: Programming Language :: Python :: 3
Classifier: Programming Language :: Python :: 3.9
Classifier: Programming Language :: Python :: 3.10
Classifier: Programming Language :: Python :: 3.11
Classifier: Programming Language :: Python :: 3.12
Requires-Dist: geneweaver-core (>=0.10.0a3,<1.0.0)
Requires-Dist: psycopg[binary] (==3.1.18)
Project-URL: Repository, https://github.com/TheJacksonLaboratory/geneweaver-db
